HISTORY.txt
README.txt
ez_setup.py
setup.cfg
setup.py
src/ClueMapperTools.egg-info/PKG-INFO
src/ClueMapperTools.egg-info/SOURCES.txt
src/ClueMapperTools.egg-info/dependency_links.txt
src/ClueMapperTools.egg-info/namespace_packages.txt
src/ClueMapperTools.egg-info/requires.txt
src/ClueMapperTools.egg-info/top_level.txt
src/ClueMapperTools.egg-info/zip-safe
src/clue/__init__.py
src/clue/tools/__init__.py
src/clue/tools/fileio.py
src/clue/tools/testing.py
src/clue/tools/tests.py