Metadata-Version: 1.0
Name: ClueMapperTools
Version: 0.6
Summary: Common tools used by ClueMapper
Home-page: UNKNOWN
Author: Rocky Burt
Author-email: rocky@serverzen.com
License: BSD
Platform: UNKNOWN
Classifier: Programming Language :: Python
Classifier: Topic :: Software Development :: Libraries :: Python Modules
